{
  "success": true,
  "data": [
    {
      "img": "https://yanxuan.nosdn.127.net/1492eee4a32cac60ef6ef53cdf1855bc.png?imageView&quality=65&thumbnail=330x330",
      "name": "轻灵碳素羽毛球拍",
      "price": 159,
      "describe": "超轻球拍，运动随心"
    },
    {
      "img": "https://yanxuan.nosdn.127.net/6522dceb8f194637a812862a58cf3935.png?imageView&quality=65&thumbnail=330x330",
      "name": "网易智造超静音变频直流风扇",
      "price": 399,
      "describe": "1个月低至1度电，像自然风一样舒服"
    },
    {
      "img": "https://yanxuan.nosdn.127.net/264bfe8941630322e2bdc3f0ccc0e244.png?imageView&quality=65&thumbnail=330x330",
      "name": "雨前西湖龙井（老茶树） 100克",
      "price": 148,
      "describe": "2018新茶，高山老茶树茶，香醇味浓"
    },
    {
      "img": "https://yanxuan.nosdn.127.net/7111fbb51c52d061fd201b49d8228b86.png?imageView&quality=65&thumbnail=330x330",
      "name": "菱形拼接束口双肩包",
      "price": 168,
      "describe": "大容量设计，轻盈储物"
    },
    {
      "img": "https://yanxuan.nosdn.127.net/f0de587302230a65d6ada5626411c15b.jpg?imageView&quality=65&thumbnail=330x330",
      "name": "Paisley欧式天丝四件套",
      "price": 599,
      "describe": "柔滑兰精天丝，清凉亲肤保湿"
    },
    {
      "img": "https://yanxuan.nosdn.127.net/d64c48b8ea7f3106d6c71389fdab4ba9.png?imageView&quality=65&thumbnail=330x330",
      "name": "健康饮水 宠物自动循环活氧饮水器",
      "price": 239,
      "describe": "活氧体验，让萌宠爱上喝水，呵护爱宠健康"
    }
  ]
}